mlrap/__init__.py
mlrap/util.py
mlrap/command/__init__.py
mlrap/command/apply.py
mlrap/command/cli.py
mlrap/command/dataset.py
mlrap/command/featurize.py
mlrap/command/model.py
mlrap/command/optim.py
mlrap/command/plot.py
mlrap/command/run.py
mlrap/command/subrun.py
mlrap/config/__init__.py
mlrap/config/current.mplstyle
mlrap/config/load_config.py
mlrap/config/optim-CONFIG.yaml
mlrap/config/run-CONFIG.yaml
mlrap/config/shap.mplstyle
mlrap/example/dielectric_constant.json.gz
mlrap/example/elastic_tensor_2015.json.gz
mlrap/main/__init__.py
mlrap/main/cross_validation.py
mlrap/main/deal_data.py
mlrap/main/draw.py
mlrap/main/featurize.py
mlrap/main/optimization.py
mlrap-1.0.0.dist-info/LICENSE.txt
mlrap-1.0.0.dist-info/METADATA
mlrap-1.0.0.dist-info/WHEEL
mlrap-1.0.0.dist-info/entry_points.txt
mlrap-1.0.0.dist-info/top_level.txt
mlrap-1.0.0.dist-info/RECORD
