Metadata-Version: 2.1
Name: mlrap
Version: 1.0.0
Summary: Machine Learning Regression Analyse Packages
Home-page: https://github.com/NianSan-H/mlrap
Author: Gang Tang, Tao Hu, Chunbao Feng
Classifier: Programming Language :: Python :: 3
Classifier: License :: OSI Approved :: MIT License
Requires-Python: >=3.8
License-File: LICENSE.txt
Requires-Dist: click
Requires-Dist: scikit-learn
Requires-Dist: xgboost
Requires-Dist: pymatgen
Requires-Dist: seaborn
Requires-Dist: bayesian-optimization
Requires-Dist: matminer
Requires-Dist: shap
Requires-Dist: CBFV
Requires-Dist: xenonpy
Requires-Dist: rdkit
Requires-Dist: mlxtend
